phifem/__init__.py
phifem/mesh_scripts.py
phifem-0.6.1.dist-info/METADATA
phifem-0.6.1.dist-info/WHEEL
phifem-0.6.1.dist-info/licenses/COPYING
phifem-0.6.1.dist-info/licenses/COPYING.lesser
phifem-0.6.1.dist-info/RECORD
