Metadata-Version: 2.4
Name: phiFEM
Version: 0.6.1
Summary: phiFEM: convenience tools to use the phiFEM immersed boundary finite element method with dolfinx.
Project-URL: Homepage, https://github.com/PhiFEM/phiFEM
Project-URL: Issues, https://github.com/PhiFEM/phiFEM/issues
Author-email: Raphaël Bulle <raphael.bulle@inria.fr>, Michel Duprez <michel.duprez@inria.fr>, Killian Vuillemot <killian.vuillemot@umontpellier.fr>
Maintainer-email: Raphaël Bulle <raphael.bulle@inria.fr>
License-Expression: GPL-3.0
License-File: COPYING
License-File: COPYING.lesser
Classifier: Operating System :: OS Independent
Classifier: Programming Language :: Python :: 3
Requires-Python: >=3.11
Requires-Dist: fenics-dolfinx>=0.9.0
